fixerio/__init__.py
fixerio/client.py
fixerio/exceptions.py
fixerio_client-1.0.0.dist-info/LICENSE
fixerio_client-1.0.0.dist-info/METADATA
fixerio_client-1.0.0.dist-info/WHEEL
fixerio_client-1.0.0.dist-info/top_level.txt
fixerio_client-1.0.0.dist-info/RECORD
